tenmao_mcp_demo/__init__.py
tenmao_mcp_demo-0.1.0.dist-info/METADATA
tenmao_mcp_demo-0.1.0.dist-info/WHEEL
tenmao_mcp_demo-0.1.0.dist-info/entry_points.txt
tenmao_mcp_demo-0.1.0.dist-info/RECORD
