Metadata-Version: 2.4
Name: tenmao-mcp-demo
Version: 0.1.0
Summary: Add your description here
Author-email: kuanglong2016 <kuanglong2016@gmail.com>
Requires-Python: >=3.13
Requires-Dist: mcp[cli]>=1.10.1
